LICENSE.txt
MANIFEST.in
README.md
setup.py
djangocms_slider/__init__.py
djangocms_slider/cms_plugins.py
djangocms_slider/models.py
djangocms_slider/locale/en/LC_MESSAGES/django.mo
djangocms_slider/locale/en/LC_MESSAGES/django.po
djangocms_slider/locale/nl/LC_MESSAGES/django.mo
djangocms_slider/locale/nl/LC_MESSAGES/django.po
djangocms_slider/migrations/0001_initial.py
djangocms_slider/migrations/0002_auto_20160728_1656.py
djangocms_slider/migrations/0003_auto_20160728_1705.py
djangocms_slider/migrations/__init__.py
djangocms_slider/templates/djangocms_slider/slide.html
djangocms_slider/templates/djangocms_slider/slider.html
djangocms_slider_easy.egg-info/PKG-INFO
djangocms_slider_easy.egg-info/SOURCES.txt
djangocms_slider_easy.egg-info/dependency_links.txt
djangocms_slider_easy.egg-info/not-zip-safe
djangocms_slider_easy.egg-info/requires.txt
djangocms_slider_easy.egg-info/top_level.txt