Metadata-Version: 1.1
Name: djangocms-slider-easy
Version: 0.2.6
Summary: A slider plugin for djangocms that lets you arrange slides like any other djangocms plugin. Fork of urga/djangocms-slider, but using easy_thumbnails.
Home-page: https://github.com/Akoten/djangocms-slider-easy
Author: Luminum Solutions
Author-email: info@akoten.com
License: BSD
Keywords: slideshow,django,cms,plugin
Platform: UNKNOWN
Classifier: Development Status :: 3 - Alpha
Classifier: Framework :: Django
Classifier: Framework :: Django :: 1.8
Classifier: Intended Audience :: Developers
Classifier: License :: OSI Approved :: BSD License
Classifier: Natural Language :: English
Classifier: Natural Language :: Dutch
Classifier: Programming Language :: Python :: 2
Classifier: Programming Language :: Python :: 2.7
Classifier: Programming Language :: Python :: 3
Classifier: Programming Language :: Python :: 3.3
Classifier: Programming Language :: Python :: 3.4
Classifier: Programming Language :: Python :: 3.5
